{"username":"Jessica","courses":{"RUS102":{"Assignments":[{"label":"HW 1","ptsEarned":"100","ptsPossible":"100","letter":"A"}],"Exams":[{"label":"Unit Test 1","ptsEarned":"95","ptsPossible":"100","letter":"A"}],"Quizzes":[{"label":"Quiz 1","ptsEarned":"97","ptsPossible":"100","letter":"A"}],"aweight":"30","eweight":"40","qweight":"30"},"CS498":{"Assignments":[{"label":"HW 1","ptsEarned":"80","ptsPossible":"100","letter":"B"}],"Exams":[{"label":"Midterm","ptsEarned":"85","ptsPossible":"100","letter":"B"}],"Quizzes":[{"label":"Quiz 1","ptsEarned":"87","ptsPossible":"100","letter":"B"}],"aweight":"30","eweight":"40","qweight":"30","assignments":null},"MA340":{"Assignments":[{"label":"HW 1","ptsEarned":"70","ptsPossible":"100","letter":"C"},{"label":"HW 2","ptsEarned":"75","ptsPossible":"100","letter":"C"}],"Exams":[{"label":"Exam 1","ptsEarned":"75","ptsPossible":"100","letter":"C"}],"Quizzes":[{"label":"Quiz 1","ptsEarned":"77","ptsPossible":"100","letter":"C"}],"aweight":"30","eweight":"40","qweight":"30"},"CS450":{"Assignments":[{"label":"HW 1","ptsEarned":"60","ptsPossible":"100","letter":"D"}],"Exams":[{"label":"Midterm","ptsEarned":"65","ptsPossible":"100","letter":"D"}],"Quizzes":[{"label":"Quiz 1","ptsEarned":"67","ptsPossible":"100","letter":"D"}],"aweight":"30","eweight":"40","qweight":"30"},"CS378":{"Assignments":[{"label":"HW 1","ptsEarned":"50","ptsPossible":"100","letter":"E"}],"Exams":[{"label":"Exam 1","ptsEarned":"55","ptsPossible":"100","letter":"E"},{"label":"Exam 2","ptsEarned":"90","ptsPossible":"100","letter":"A"}],"Quizzes":[{"label":"Quiz 1","ptsEarned":"57","ptsPossible":"100","letter":"E"}],"aweight":"30","eweight":"40","qweight":"30"},"":{"Assignments":[],"Exams":[],"Quizzes":[],"aweight":"","eweight":"","qweight":""}}}